Metadata-Version: 1.0
Name: catkin-cppcheck
Version: 0.0.4
Summary: Run cppcheck on catkin packages
Home-page: UNKNOWN
Author: Natesh Narain
Author-email: nnaraindev@gmail.com
License: MIT
Keywords: catkin ros cppcheck c++
Platform: UNKNOWN
